bmbftnl/console.py
bmbftnl/csvimporter.py
bmbftnl/participant.py
bmbftnl/pdfexporter.py
bmbftnl-0.1.2.dist-info/LICENSE
bmbftnl-0.1.2.dist-info/METADATA
bmbftnl-0.1.2.dist-info/WHEEL
bmbftnl-0.1.2.dist-info/entry_points.txt
bmbftnl-0.1.2.dist-info/RECORD
