Metadata-Version: 2.3
Name: bmbftnl
Version: 0.1.2
Summary: Automatisches Ausfüllen von Teilnehmendenlisten des BMBF mit Namen, Standort und Studierendenstatus
License: MIT
Keywords: bmbf,teilnehmende
Author: Florian Katerndahl
Author-email: florian@katerndahl.com
Requires-Python: >=3.8,<4.0
Classifier: License :: OSI Approved :: MIT License
Classifier: Programming Language :: Python :: 3
Classifier: Programming Language :: Python :: 3.8
Classifier: Programming Language :: Python :: 3.9
Classifier: Programming Language :: Python :: 3.10
Classifier: Programming Language :: Python :: 3.11
Classifier: Programming Language :: Python :: 3.12
Classifier: Programming Language :: Python :: 3.13
Requires-Dist: charset-normalizer (>=3.4.4,<4.0.0)
Requires-Dist: pypdf (>=5.6.0,<6.0.0)
Requires-Dist: tqdm (>=4.67.1,<5.0.0)
Project-URL: Repository, https://github.com/Florian-Katerndahl/bmbfTNL
